clonellm/__init__.py
clonellm/_base.py
clonellm/_prompt.py
clonellm/core.py
clonellm/embed.py
clonellm/enums.py
clonellm/memory.py
clonellm/models.py
clonellm/py.typed
clonellm-0.4.0.dist-info/LICENSE
clonellm-0.4.0.dist-info/METADATA
clonellm-0.4.0.dist-info/WHEEL
clonellm-0.4.0.dist-info/RECORD
