Metadata-Version: 2.3
Name: clonellm
Version: 0.4.0
Summary: Python package to create an AI clone of yourself using LLMs.
License: MIT
Keywords: python,ai,llm,rag
Author: Mehdi Samsami
Author-email: mehdisamsami@live.com
Requires-Python: >=3.10,<3.14
Classifier: License :: OSI Approved :: MIT License
Classifier: Programming Language :: Python :: 3
Classifier: Programming Language :: Python :: 3.10
Classifier: Programming Language :: Python :: 3.11
Classifier: Programming Language :: Python :: 3.12
Classifier: Programming Language :: Python :: 3.13
Provides-Extra: chroma
Provides-Extra: faiss
Requires-Dist: faiss-cpu ; extra == "faiss"
Requires-Dist: langchain (>=0.1.17,<0.2.0)
Requires-Dist: langchain-chroma ; extra == "chroma"
Requires-Dist: legacy-cgi (>=2.6.2) ; python_version >= "3.13"
Requires-Dist: litellm (>=1.36.0,<2.0.0)
Requires-Dist: pydantic (>=2.8.0) ; python_full_version >= "3.12.4"
Project-URL: Repository, https://github.com/msamsami/clonellm
